unblock/__init__.py
unblock/common.py
unblock/core.py
get_unblock-0.1.0.dist-info/METADATA
get_unblock-0.1.0.dist-info/WHEEL
get_unblock-0.1.0.dist-info/licenses/LICENSE
get_unblock-0.1.0.dist-info/RECORD
