Metadata-Version: 2.3
Name: get-unblock
Version: 0.1.0
Summary: unblock comes with utilities that can be used to convert synchronous functions to async for use in event loop
License-File: LICENSE
Requires-Python: >=3.7
